hsapi_client/__init__.py
hsapi_client/apikeys.py
hsapi_client/config.py
hsapi_client/model.py
hsapi_client/nodes.py
hsapi_client/policies.py
hsapi_client/preauthkeys.py
hsapi_client/routes.py
hsapi_client/schemas.py
hsapi_client/users.py
hsapi_client-0.9.9.dist-info/LICENSE
hsapi_client-0.9.9.dist-info/METADATA
hsapi_client-0.9.9.dist-info/WHEEL
hsapi_client-0.9.9.dist-info/RECORD
