Metadata-Version: 2.1
Name: hsapi-client
Version: 0.9.9
Summary: Headscale API client
License: BSD
Author: Andrea Mistrali
Author-email: andrea@mistrali.pw
Requires-Python: >=3.11,<4.0
Classifier: License :: Other/Proprietary License
Classifier: Programming Language :: Python :: 3
Classifier: Programming Language :: Python :: 3.11
Classifier: Programming Language :: Python :: 3.12
Requires-Dist: pydantic (>=2.7.4,<3.0.0)
Requires-Dist: pydantic-settings (>=2.3.4,<3.0.0)
Requires-Dist: pyjson5 (>=1.6.6,<2.0.0)
Requires-Dist: requests (>=2.32.3,<3.0.0)
